lensedGW/__init__.py
lensedGW/main.py
lensedGW-1.0.10.dist-info/LICENSE
lensedGW-1.0.10.dist-info/METADATA
lensedGW-1.0.10.dist-info/WHEEL
lensedGW-1.0.10.dist-info/entry_points.txt
lensedGW-1.0.10.dist-info/top_level.txt
lensedGW-1.0.10.dist-info/RECORD
