Metadata-Version: 2.1
Name: lensedGW
Version: 1.0.10
Summary: lensed waveform for point mass model
Home-page: https://github.com/yourusername/addone
Author: Your Name
Author-email: your_email@example.com
Classifier: Programming Language :: Python :: 3
Classifier: License :: OSI Approved :: MIT License
Classifier: Operating System :: OS Independent
Requires-Python: >=3.6
License-File: LICENSE
